beatdbscheduler/__init__.py
beatdbscheduler/schedulers.py
beatdbscheduler/model/__init__.py
beatdbscheduler/model/base.py
beatdbscheduler/model/model.py
celerybeat_sqlalchemy_scheduler-0.1.1.dist-info/DESCRIPTION.rst
celerybeat_sqlalchemy_scheduler-0.1.1.dist-info/METADATA
celerybeat_sqlalchemy_scheduler-0.1.1.dist-info/RECORD
celerybeat_sqlalchemy_scheduler-0.1.1.dist-info/WHEEL
celerybeat_sqlalchemy_scheduler-0.1.1.dist-info/metadata.json
celerybeat_sqlalchemy_scheduler-0.1.1.dist-info/top_level.txt
