Metadata-Version: 2.0
Name: celerybeat-sqlalchemy-scheduler
Version: 0.1.1
Summary: Celery Beat Scheduler which stores entries in a database.
Home-page: UNKNOWN
Author: Richard O'Dwyer
Author-email: richard@richard.do
License: Apache 2
Platform: UNKNOWN
Classifier: Intended Audience :: Developers
Classifier: Operating System :: OS Independent
Classifier: Programming Language :: Python
Classifier: Programming Language :: Python :: 3
Classifier: Programming Language :: Python :: 3.6
Requires-Dist: celery
Requires-Dist: sqlalchemy
Requires-Dist: SQLAlchemy-Utils
